{
  "trackers": [
    {
      "type": "cloudflare",
      "url": "https://challenges.cloudflare.com/turnstile/v0/b/aeb70db32f0f/api.js?onload=BQUvh4&render=explicit",
      "details": {
        "id": "cloudflare",
        "message": "Host files locally"
      }
    },
    {
      "type": "cloudflare",
      "url": "https://challenges.cloudflare.com/cdn-cgi/challenge-platform/h/b/turnstile/if/ov2/av0/rcv0/0/xgpu2/0x4AAAAAAADnPIDROrmt1Wwj/light/normal",
      "details": {
        "id": "cloudflare",
        "message": "Host files locally"
      }
    }
  ],
  "cookies": [
    {
      "name": "__cf_bm",
      "value": "FmTA0Nmj1UClpclN7GH45JGDE9sGe5fO5EK0AoiiP0U-1710034096-1.0.1.1-W8aqUOZODZ1j37AwJKKSc2PQq7L1nx9MnwZqlgNTXmoToeRFUs1EeD4crv1TXB8XwjxmchgIW2j3QC7zJv2wcQ",
      "domain": ".aft.gouv.fr",
      "path": "/",
      "expires": 1710035896.266985,
      "size": 156,
      "httpOnly": true,
      "secure": true,
      "session": false,
      "sameSite": "None",
      "sameParty": false,
      "sourceScheme": "Secure",
      "sourcePort": 443
    }
  ],
  "headers": {
    "accept-ch": "Sec-CH-UA-Bitness, Sec-CH-UA-Arch, Sec-CH-UA-Full-Version, Sec-CH-UA-Mobile, Sec-CH-UA-Model, Sec-CH-UA-Platform-Version, Sec-CH-UA-Full-Version-List, Sec-CH-UA-Platform, Sec-CH-UA, UA-Bitness, UA-Arch, UA-Full-Version, UA-Mobile, UA-Model, UA-Platform-Version, UA-Platform, UA",
    "alt-svc": "h3=\":443\"; ma=86400",
    "cache-control": "private, max-age=0, no-store, no-cache, must-revalidate, post-check=0, pre-check=0",
    "cf-chl-out": "7KLf0mjKDTnDwj5FpgQ58yhJph2WUHoD1eSrNJAsEAe5d43O6EnA1Qsv/xsIUHwFPnTUcevJyo2YG9BvQ++/gNq7CzfWCc0G8InMlxBXTuTFh177ajvUwSsBfZhJq9FrWyOOJzZiZvo8v5ofXk2wHw==$WyvxlCxXjczSQt+oxWgGig==",
    "cf-mitigated": "challenge",
    "cf-ray": "861f86ed29f26fc6-CDG",
    "content-encoding": "br",
    "content-type": "text/html; charset=UTF-8",
    "cross-origin-embedder-policy": "require-corp",
    "cross-origin-opener-policy": "same-origin",
    "cross-origin-resource-policy": "same-origin",
    "date": "Sun, 10 Mar 2024 01:28:16 GMT",
    "expires": "Thu, 01 Jan 1970 00:00:01 GMT",
    "origin-agent-cluster": "?1",
    "permissions-policy": "accelerometer=(),autoplay=(),browsing-topics=(),camera=(),clipboard-read=(),clipboard-write=(),geolocation=(),gyroscope=(),hid=(),interest-cohort=(),magnetometer=(),microphone=(),payment=(),publickey-credentials-get=(),screen-wake-lock=(),serial=(),sync-xhr=(),usb=()",
    "referrer-policy": "same-origin",
    "server": "cloudflare",
    "set-cookie": "__cf_bm=FmTA0Nmj1UClpclN7GH45JGDE9sGe5fO5EK0AoiiP0U-1710034096-1.0.1.1-W8aqUOZODZ1j37AwJKKSc2PQq7L1nx9MnwZqlgNTXmoToeRFUs1EeD4crv1TXB8XwjxmchgIW2j3QC7zJv2wcQ; path=/; expires=Sun, 10-Mar-24 01:58:16 GMT; domain=.aft.gouv.fr; HttpOnly; Secure; SameSite=None",
    "strict-transport-security": "max-age=15552000; includeSubDomains; preload",
    "vary": "Accept-Encoding",
    "x-content-type-options": "nosniff",
    "x-frame-options": "SAMEORIGIN"
  },
  "endpoints": [
    {
      "hostname": "www.aft.gouv.fr",
      "ip": "141.101.90.97",
      "geoip": {
        "continent": {
          "code": "NA",
          "geoname_id": 6255149,
          "names": {
            "de": "Nordamerika",
            "en": "North America",
            "es": "Norteamérica",
            "fr": "Amérique du Nord",
            "ja": "北アメリカ",
            "pt-BR": "América do Norte",
            "ru": "Северная Америка",
            "zh-CN": "北美洲"
          }
        },
        "country": {
          "geoname_id": 6252001,
          "iso_code": "US",
          "names": {
            "de": "USA",
            "en": "United States",
            "es": "Estados Unidos",
            "fr": "États Unis",
            "ja": "アメリカ",
            "pt-BR": "EUA",
            "ru": "США",
            "zh-CN": "美国"
          }
        },
        "location": {
          "accuracy_radius": 1000,
          "latitude": 37.751,
          "longitude": -97.822,
          "time_zone": "America/Chicago"
        },
        "registered_country": {
          "geoname_id": 6252001,
          "iso_code": "US",
          "names": {
            "de": "USA",
            "en": "United States",
            "es": "Estados Unidos",
            "fr": "États Unis",
            "ja": "アメリカ",
            "pt-BR": "EUA",
            "ru": "США",
            "zh-CN": "美国"
          }
        }
      }
    },
    {
      "hostname": "challenges.cloudflare.com",
      "ip": "104.17.3.184",
      "geoip": {
        "registered_country": {
          "geoname_id": 6252001,
          "iso_code": "US",
          "names": {
            "de": "USA",
            "en": "United States",
            "es": "Estados Unidos",
            "fr": "États Unis",
            "ja": "アメリカ",
            "pt-BR": "EUA",
            "ru": "США",
            "zh-CN": "美国"
          }
        }
      }
    }
  ]
}
